douroucoulisay/__init__.py
douroucoulisay/douroucoulisay.py
douroucoulisay/assets/douroucouli1.txt
douroucoulisay/assets/douroucouli2.txt
douroucoulisay/assets/douroucouli3.txt
douroucoulisay/assets/douroucouli4.txt
douroucoulisay/assets/douroucouli5.txt
douroucoulisay/assets/douroucouli6.txt
douroucoulisay-0.3.7.dist-info/LICENSE.txt
douroucoulisay-0.3.7.dist-info/METADATA
douroucoulisay-0.3.7.dist-info/WHEEL
douroucoulisay-0.3.7.dist-info/entry_points.txt
douroucoulisay-0.3.7.dist-info/top_level.txt
douroucoulisay-0.3.7.dist-info/RECORD
