Metadata-Version: 2.1
Name: douroucoulisay
Version: 0.3.7
Summary: A package to print messages with douroucouli ASCII art.
Home-page: https://github.com/douroucoulis-fr/douroucoulisay.git
Author: Aotus Parisinus
Author-email: douroucoulis-fr@gmail.com
Classifier: Programming Language :: Python :: 3
Classifier: License :: OSI Approved :: MIT License
Classifier: Operating System :: OS Independent
License-File: LICENSE.txt
